odoo/addons/account_skip_bank_reconciliation/README.rst
odoo/addons/account_skip_bank_reconciliation/__init__.py
odoo/addons/account_skip_bank_reconciliation/__manifest__.py
odoo/addons/account_skip_bank_reconciliation/i18n/account_skip_bank_reconciliation.pot
odoo/addons/account_skip_bank_reconciliation/i18n/nl_NL.po
odoo/addons/account_skip_bank_reconciliation/models/__init__.py
odoo/addons/account_skip_bank_reconciliation/models/account_account.py
odoo/addons/account_skip_bank_reconciliation/models/account_journal.py
odoo/addons/account_skip_bank_reconciliation/models/account_reconcile_model.py
odoo/addons/account_skip_bank_reconciliation/models/reconciliation_widget.py
odoo/addons/account_skip_bank_reconciliation/readme/CONTRIBUTORS.rst
odoo/addons/account_skip_bank_reconciliation/readme/DESCRIPTION.rst
odoo/addons/account_skip_bank_reconciliation/readme/USAGE.rst
odoo/addons/account_skip_bank_reconciliation/static/description/icon.png
odoo/addons/account_skip_bank_reconciliation/static/description/index.html
odoo/addons/account_skip_bank_reconciliation/views/account_journal_view.xml
odoo/addons/account_skip_bank_reconciliation/views/account_view.xml
odoo13_addon_account_skip_bank_reconciliation-13.0.1.0.1.dev4.dist-info/METADATA
odoo13_addon_account_skip_bank_reconciliation-13.0.1.0.1.dev4.dist-info/WHEEL
odoo13_addon_account_skip_bank_reconciliation-13.0.1.0.1.dev4.dist-info/top_level.txt
odoo13_addon_account_skip_bank_reconciliation-13.0.1.0.1.dev4.dist-info/RECORD
